rosny/__init__.py
rosny/abstract.py
rosny/compose.py
rosny/loop.py
rosny/process.py
rosny/signal.py
rosny/state.py
rosny/thread.py
rosny/timing.py
rosny/utils.py
rosny-0.1.0.dist-info/LICENSE
rosny-0.1.0.dist-info/METADATA
rosny-0.1.0.dist-info/WHEEL
rosny-0.1.0.dist-info/top_level.txt
rosny-0.1.0.dist-info/RECORD
