Metadata-Version: 2.1
Name: rosny
Version: 0.1.0
Summary: Lightweight library for building concurrent systems.
Author-email: Ruslan Baikulov <ruslan1123@gmail.com>
License: MIT License
Project-URL: Repository, https://github.com/lRomul/rosny
Project-URL: Documentation, https://lromul.github.io/rosny
Classifier: Development Status :: 4 - Beta
Classifier: License :: OSI Approved :: MIT License
Classifier: Intended Audience :: Developers
Classifier: Operating System :: OS Independent
Classifier: Programming Language :: Python
Classifier: Programming Language :: Python :: 3
Classifier: Programming Language :: Python :: 3.8
Classifier: Programming Language :: Python :: 3.9
Classifier: Programming Language :: Python :: 3.10
Classifier: Programming Language :: Python :: 3.11
Classifier: Programming Language :: Python :: 3.12
Classifier: Topic :: Software Development
Classifier: Topic :: Software Development :: Libraries
Classifier: Topic :: Software Development :: Libraries :: Python Modules
Requires-Python: >=3.8
License-File: LICENSE
Provides-Extra: docs
Requires-Dist: mkdocs ==1.5.3 ; extra == 'docs'
Requires-Dist: mkdocs-material ==9.5.18 ; extra == 'docs'
Provides-Extra: examples
Requires-Dist: opencv-python ==4.9.0.80 ; extra == 'examples'
Requires-Dist: mediapipe ==0.10.9 ; extra == 'examples'
Provides-Extra: tests
Requires-Dist: pytest ==8.1.1 ; extra == 'tests'
Requires-Dist: pytest-cov ==5.0.0 ; extra == 'tests'
Requires-Dist: mypy ==1.9.0 ; extra == 'tests'
Requires-Dist: ruff ==0.3.7 ; extra == 'tests'
